pymsfilereader/MSFileReader.py
pymsfilereader/__init__.py
pymsfilereader-1.0.1.dist-info/LICENSE.md
pymsfilereader-1.0.1.dist-info/METADATA
pymsfilereader-1.0.1.dist-info/WHEEL
pymsfilereader-1.0.1.dist-info/top_level.txt
pymsfilereader-1.0.1.dist-info/RECORD
